setup.py
common/__init__.py
common/constant.py
common/decorators.py
common/descriptors.py
common/messanger.py
common/meta.py
msg_srv_project.egg-info/PKG-INFO
msg_srv_project.egg-info/SOURCES.txt
msg_srv_project.egg-info/dependency_links.txt
msg_srv_project.egg-info/requires.txt
msg_srv_project.egg-info/top_level.txt
server/__init__.py
server/add_user.py
server/del_user.py
server/srv_db.py
server/srv_gui.py
unit_tests/__init__.py
unit_tests/test_client.py
unit_tests/test_messanger.py
unit_tests/test_server.py