Metadata-Version: 1.0
Name: msg-srv-project
Version: 0.0.1
Summary: message server
Home-page: UNKNOWN
Author: Oleg Lo
Author-email: olomakin@ya.ru
License: UNKNOWN
Platform: UNKNOWN
